{"type": "FeatureCollection", "features": [{"type": "Feature", "geometry": {"type": "Point", "coordinates": [179.19937444001198, -8.515221575847221]}, "properties": {"osm_id": 651129681, "osm_type": "node", "completeness": 12.5, "amenity": "hospital", "healthcare": "hospital", "name": "Princess Margaret Hospital", "operator": "", "source": "", "speciality": "", "operator_type": "", "operational_status": "", "opening_hours": "", "beds": "", "staff_doctors": "", "staff_nurses": "", "health_amenity_type": "", "dispensing": "", "wheelchair": "", "emergency": "", "insurance": "", "water_source": "", "electricity": "", "is_in_health_area": "", "is_in_health_zone": "", "url": "", "addr_housenumber": "", "addr_street": "", "addr_postcode": "", "addr_city": "", "changeset_id": 89132821.0, "changeset_version": 5.0, "changeset_timestamp": "2020-08-08T16:19:08Z", "uuid": "9452b67b31a24a1884ae6c61415f2e80"}}]}